cwlkernel/AutoCompleteEngine.py
cwlkernel/CWLBuilder.py
cwlkernel/CWLExecuteConfigurator.py
cwlkernel/CWLKernel.py
cwlkernel/CWLLogger.py
cwlkernel/CWLLoggerStorageManager.py
cwlkernel/CoreExecutor.py
cwlkernel/IOManager.py
cwlkernel/__init__.py
cwlkernel/__main__.py
cwlkernel/kernel_magics.py
cwlkernel/cwlrepository/CWLComponent.py
cwlkernel/cwlrepository/__init__.py
cwlkernel/cwlrepository/cwlrepository.py
cwlkernel/git/CWLGitResolver.py
cwlkernel/git/__init__.py
cwlkernel-0.0.4.data/data/share/jupyter/kernels/cwlkernel/kernel.json
cwlkernel-0.0.4.data/data/share/jupyter/kernels/cwlkernel/logo-32x32.png
cwlkernel-0.0.4.data/data/share/jupyter/kernels/cwlkernel/logo-64x64.png
cwlkernel-0.0.4.dist-info/LICENSE
cwlkernel-0.0.4.dist-info/METADATA
cwlkernel-0.0.4.dist-info/WHEEL
cwlkernel-0.0.4.dist-info/top_level.txt
cwlkernel-0.0.4.dist-info/RECORD
