Metadata-Version: 2.1
Name: cwlkernel
Version: 0.0.4
Summary: CWL Jupyter Notebook Kernel
Home-page: https://github.com/giannisdoukas/CWLJNIKernel
Author: Yannis Doukas
Author-email: giannisdoukas2311@gmail.com
License: UNKNOWN
Platform: UNKNOWN
Classifier: Programming Language :: Python :: 3
Classifier: License :: OSI Approved :: Apache Software License
Classifier: Operating System :: MacOS
Classifier: Operating System :: POSIX
Classifier: Development Status :: 2 - Pre-Alpha
Classifier: Framework :: IPython
Classifier: Programming Language :: Python :: 3.6
Classifier: Programming Language :: Python :: 3.7
Classifier: Programming Language :: Python :: 3.8
Requires-Python: >=3.6
Requires-Dist: cwltool (>=3.0.20200720165847)
Requires-Dist: jsonschema (>=3.2.0)
Requires-Dist: jupyter-client (>=5.3.4)
Requires-Dist: jupyter-core (>=4.6.3)
Requires-Dist: psutil (>=5.7.0)
Requires-Dist: ruamel.yaml (<=0.16.5,>=0.12.4)
Requires-Dist: PyYAML (>=5.3.1)
Requires-Dist: pandas (>=1.0.4)
Requires-Dist: notebook (>=6.0.3)
Requires-Dist: requests (>=2.23.0)
Requires-Dist: pygtrie (>=2.3.3)
Requires-Dist: pydot (>=1.4.1)
